route_rules/__init__.py
route_rules/__init__.pyi
route_rules/_version.py
route_rules/_version.pyi
route_rules/py.typed
route_rules/core/__init__.py
route_rules/core/__init__.pyi
route_rules/core/_ruleset.py
route_rules/export/__init__.py
route_rules/export/__init__.pyi
route_rules/export/_abc.py
route_rules/export/_mihomo.py
route_rules/gen/__init__.py
route_rules/gen/__init__.pyi
route_rules/gen/_builder.py
route_rules/gen/_config.py
route_rules/gen/_meta.py
route_rules/gen/_recipe.py
route_rules/provider/__init__.py
route_rules/provider/__init__.pyi
route_rules/provider/_abc.py
route_rules/provider/_registry.py
route_rules/provider/mihomo/__init__.py
route_rules/provider/mihomo/__init__.pyi
route_rules/provider/mihomo/_decode.py
route_rules/provider/mihomo/_enum.py
route_rules/provider/mihomo/_provider.py
route_rules/utils/__init__.py
route_rules/utils/__init__.pyi
route_rules/utils/_download.py
route_rules-0.3.1.dist-info/METADATA
route_rules-0.3.1.dist-info/WHEEL
route_rules-0.3.1.dist-info/licenses/LICENSE
route_rules-0.3.1.dist-info/RECORD
