Metadata-Version: 2.4
Name: route-rules
Version: 0.3.1
Project-URL: Changelog, https://github.com/liblaf/route-rules/blob/main/CHANGELOG.md
Project-URL: Documentation, https://liblaf.github.io/route-rules/
Project-URL: Funding, https://github.com/liblaf/route-rules?sponsor=1
Project-URL: Homepage, https://github.com/liblaf/route-rules
Project-URL: Issue Tracker, https://github.com/liblaf/route-rules/issues
Project-URL: Release Notes, https://github.com/liblaf/route-rules/releases
Project-URL: Source Code, https://github.com/liblaf/route-rules
Author-email: liblaf <30631553+liblaf@users.noreply.github.com>
License-Expression: MIT
License-File: LICENSE
Classifier: Development Status :: 4 - Beta
Classifier: Intended Audience :: Developers
Classifier: License :: OSI Approved
Classifier: License :: OSI Approved :: MIT License
Classifier: Operating System :: OS Independent
Classifier: Programming Language :: Python
Classifier: Programming Language :: Python :: 3
Classifier: Programming Language :: Python :: 3.12
Classifier: Programming Language :: Python :: 3.13
Classifier: Typing :: Typed
Requires-Python: >=3.12
Requires-Dist: anyio<5,>=4
Requires-Dist: autoregistry<2,>=1
Requires-Dist: cachetools-async<0.0.6,>=0.0.5
Requires-Dist: cachetools<7,>=6
Requires-Dist: cytoolz<2,>=1
Requires-Dist: hishel[httpx]<2,>=1
Requires-Dist: httpx[socks]<0.29,>=0.28
Requires-Dist: lazy-loader<0.5,>=0.4
Requires-Dist: liblaf-grapes<10,>=9
Requires-Dist: prettytable<4,>=3
Requires-Dist: python-slugify<9,>=8
Requires-Dist: validators<0.36,>=0.35
